hvpy/__init__.py
hvpy/config.py
hvpy/conftest.py
hvpy/core.py
hvpy/datasource.py
hvpy/event.py
hvpy/facade.py
hvpy/helpers.py
hvpy/io.py
hvpy/parameters.py
hvpy/utils.py
hvpy/version.py
hvpy/api_groups/__init__.py
hvpy/api_groups/communications/__init__.py
hvpy/api_groups/communications/get_news_feed.py
hvpy/api_groups/communications/shorten_url.py
hvpy/api_groups/communications/tests/__init__.py
hvpy/api_groups/communications/tests/test_get_news_feed.py
hvpy/api_groups/communications/tests/test_shorten_url.py
hvpy/api_groups/jpeg2000/__init__.py
hvpy/api_groups/jpeg2000/get_jp2_header.py
hvpy/api_groups/jpeg2000/get_jp2_image.py
hvpy/api_groups/jpeg2000/get_jpx.py
hvpy/api_groups/jpeg2000/get_jpx_closest_to_mid_point.py
hvpy/api_groups/jpeg2000/get_status.py
hvpy/api_groups/jpeg2000/tests/__init__.py
hvpy/api_groups/jpeg2000/tests/test_get_jp2_header.py
hvpy/api_groups/jpeg2000/tests/test_get_jp2_image.py
hvpy/api_groups/jpeg2000/tests/test_get_jpx.py
hvpy/api_groups/jpeg2000/tests/test_get_jpx_closest_to_mid_point.py
hvpy/api_groups/jpeg2000/tests/test_get_status.py
hvpy/api_groups/movies/__init__.py
hvpy/api_groups/movies/download_movie.py
hvpy/api_groups/movies/get_movie_status.py
hvpy/api_groups/movies/queue_movie.py
hvpy/api_groups/movies/re_queue_movie.py
hvpy/api_groups/movies/tests/__init__.py
hvpy/api_groups/movies/tests/test_download_movie.py
hvpy/api_groups/movies/tests/test_get_movie_status.py
hvpy/api_groups/movies/tests/test_queue_movie.py
hvpy/api_groups/movies/tests/test_re_queue_movie.py
hvpy/api_groups/official_clients/__init__.py
hvpy/api_groups/official_clients/get_closest_image.py
hvpy/api_groups/official_clients/get_data_sources.py
hvpy/api_groups/official_clients/tests/__init__.py
hvpy/api_groups/official_clients/tests/test_get_closest_image.py
hvpy/api_groups/official_clients/tests/test_get_data_sources.py
hvpy/api_groups/screenshots/download_screenshot.py
hvpy/api_groups/screenshots/get_tile.py
hvpy-1.1.0.dist-info/LICENSE.rst
hvpy-1.1.0.dist-info/METADATA
hvpy-1.1.0.dist-info/WHEEL
hvpy-1.1.0.dist-info/top_level.txt
hvpy-1.1.0.dist-info/zip-safe
hvpy-1.1.0.dist-info/RECORD
