Metadata-Version: 2.1
Name: hvpy
Version: 1.1.0
Summary: Helioviewer Python API Wrapper
Home-page: https://helioviewer.org/
Author: The Helioviewer Project
Author-email: contact@helioviewer.org
License: BSD 2-Clause
Keywords: solar physics,solar,science,sun,data,helioviewer
Platform: any
Classifier: Development Status :: 5 - Production/Stable
Classifier: Intended Audience :: Science/Research
Classifier: License :: OSI Approved :: BSD License
Classifier: Natural Language :: English
Classifier: Operating System :: OS Independent
Classifier: Programming Language :: Python
Classifier: Programming Language :: Python :: 3
Classifier: Programming Language :: Python :: 3.8
Classifier: Programming Language :: Python :: 3.9
Classifier: Programming Language :: Python :: 3.10
Classifier: Programming Language :: Python :: 3.11
Classifier: Topic :: Scientific/Engineering :: Physics
Requires-Python: >=3.8
License-File: licenses/LICENSE.rst
Requires-Dist: requests (>=2.27.0)
Requires-Dist: pydantic (>=2.0.0)
Requires-Dist: pydantic-settings (>=2.0.0)
Provides-Extra: docs
Requires-Dist: sphinx (<6.0.0) ; extra == 'docs'
Requires-Dist: sphinx-autodoc-typehints ; extra == 'docs'
Requires-Dist: sphinx-automodapi ; extra == 'docs'
Requires-Dist: sphinx-book-theme ; extra == 'docs'
Provides-Extra: tests
Requires-Dist: pytest-astropy (>=0.10) ; extra == 'tests'
Requires-Dist: pytest-timeout ; extra == 'tests'
Requires-Dist: pytest (>=6.0) ; extra == 'tests'
